stuartplot/__init__.py
stuartplot/stuartplot.py
stuartplot-0.0.9.dist-info/METADATA
stuartplot-0.0.9.dist-info/WHEEL
stuartplot-0.0.9.dist-info/top_level.txt
stuartplot-0.0.9.dist-info/RECORD
