Metadata-Version: 2.1
Name: stuartplot
Version: 0.0.9
Summary: Matplotlib wrapper
Home-page: https://github.com/stuart-watt/stuart_plot
Author: Stuart Watt
License: UNKNOWN
Platform: UNKNOWN
Requires-Python: >=3.6
Requires-Dist: matplotlib
